{
  "learning_rate_lora": 0.0002, "lora_r": 16, "lora_alpha": 32, "lora_dropout": 0.05,
  "warmup_ratio": 0.03, "max_grad_norm": 1.0, "weight_decay": 0.0, "max_pixels": 200704,
  "input_field": "attribute_spec_text",

  "group_size": 8, "rollout_temperature": 0.7, "rollout_top_p": 0.9, "prompts_per_round": 8,
  "grpo_lr": 5e-6, "warmup_steps": 10, "grad_accum": 8, "update_epochs": 1,
  "clip_eps": 0.2, "kl_beta": 0.05, "adv_eps": 1e-4, "entropy_coef": 0.0, "total_steps": 500,
  "ckpt_every": 20, "eval_every": 20, "eval_limit": 64,
  "collapse_penalty": 0.25, "delta_e_weight": 0.0
}
